simple_lama_inpainting/__init__.py
simple_lama_inpainting/cli.py
simple_lama_inpainting/models/__init__.py
simple_lama_inpainting/models/model.py
simple_lama_inpainting/utils/__init__.py
simple_lama_inpainting/utils/util.py
simple_lama_inpainting-0.1.1.dist-info/LICENSE
simple_lama_inpainting-0.1.1.dist-info/METADATA
simple_lama_inpainting-0.1.1.dist-info/WHEEL
simple_lama_inpainting-0.1.1.dist-info/entry_points.txt
simple_lama_inpainting-0.1.1.dist-info/RECORD
