Metadata-Version: 2.1
Name: simple-lama-inpainting
Version: 0.1.1
Summary: 
Author: enesmsahin
Author-email: enessahin@outlook.com
Requires-Python: >=3.10,<4.0
Classifier: Programming Language :: Python :: 3
Classifier: Programming Language :: Python :: 3.10
Classifier: Programming Language :: Python :: 3.11
Requires-Dist: fire (>=0.5.0,<0.6.0)
Requires-Dist: numpy (>=1.25.1,<2.0.0)
Requires-Dist: opencv-python (>=4.8.0.74,<5.0.0.0)
Requires-Dist: pillow (>=10.0.0,<11.0.0)
Requires-Dist: torch (>=1.13.1,!=2.0.1)
Requires-Dist: torchvision (>=0.14.1)
